PyMD/MDGenerator.py
PyMD/__init__.py
PyMD/tools/__init__.py
PyMD/tools/sections.py
PyMD/tools/utils.py
RPyMD-1.0.0.dist-info/LICENSE
RPyMD-1.0.0.dist-info/METADATA
RPyMD-1.0.0.dist-info/WHEEL
RPyMD-1.0.0.dist-info/top_level.txt
RPyMD-1.0.0.dist-info/RECORD
