Metadata-Version: 2.1
Name: RPyMD
Version: 1.0.0
Summary: Library for recording in a markdown file.
Author-email: Randall Fowler <randallfowler77@yahoo.com>
License: MIT License
Project-URL: Homepage, https://github.com/Th3RandyMan/PyMD
Keywords: markdown,MarkDown,generator,report,results,evaluation
Requires-Python: >=3.6
License-File: LICENSE
Requires-Dist: mdutils
Requires-Dist: matplotlib
Requires-Dist: pandas
